[
 {
  "Chinese": "竞选",
  "English": [
   "campaign",
   "election",
   "running",
   "race",
   "candidate",
   "campaigned",
   "electoral"
  ],
  "词性": [
   "n.",
   "名词"
  ]
 },
 {
  "Chinese": "运动",
  "English": [
   "movement",
   "sports",
   "motion",
   "exercise",
   "campaign",
   "moving",
   "athletic"
  ],
  "词性": [
   "n.",
   "名词"
  ]
 },
 {
  "Chinese": "战役",
  "English": [
   "battle",
   "campaign"
  ],
  "词性": [
   "n.",
   "名词"
  ]
 },
 {
  "Chinese": "竞选活动",
  "English": [
   "campaign",
   "electioneering"
  ],
  "词性": [
   "n.",
   "名词"
  ]
 },
 {
  "Chinese": "活动",
  "English": [
   "activities",
   "events",
   "active",
   "campaign",
   "movement"
  ],
  "词性": [
   "n.",
   "名词"
  ]
 },
 {
  "Chinese": "行动",
  "English": [
   "action",
   "operation",
   "act",
   "move",
   "acting",
   "initiative",
   "campaign"
  ],
  "词性": [
   "n.",
   "名词"
  ]
 },
 {
  "Chinese": "作战",
  "English": [
   "combat",
   "operations",
   "fight",
   "battle",
   "operational",
   "war",
   "warfare",
   "campaign"
  ],
  "词性": [
   "n.",
   "名词"
  ]
 },
 {
  "Chinese": "宣传",
  "English": [
   "publicity",
   "propaganda",
   "promotion",
   "publicize",
   "promotional",
   "advocacy",
   "advertise",
   "campaign"
  ],
  "词性": [
   "n.",
   "名词"
  ]
 }
]