[
 {
  "Chinese": "原名",
  "English": [
   "formerly",
   "formerly known"
  ],
  "词性": [
   "adv.",
   "副词"
  ]
 },
 {
  "Chinese": "以前",
  "English": [
   "before",
   "ago",
   "used",
   "previous",
   "'ve",
   "previously",
   "former",
   "past",
   "formerly"
  ],
  "词性": [
   "adv.",
   "副词"
  ]
 },
 {
  "Chinese": "前身",
  "English": [
   "predecessor",
   "formerly known",
   "formerly",
   "precursor",
   "successor",
   "forerunner"
  ],
  "词性": [
   "adv.",
   "副词"
  ]
 },
 {
  "Chinese": "从前",
  "English": [
   "before",
   "former",
   "formerly",
   "previously"
  ],
  "词性": [
   "adv.",
   "副词"
  ]
 },
 {
  "Chinese": "原",
  "English": [
   "original",
   "primary",
   "former",
   "raw",
   "indigenous",
   "originally",
   "yuan",
   "formerly"
  ],
  "词性": [
   "adv.",
   "副词"
  ]
 },
 {
  "Chinese": "以往",
  "English": [
   "past",
   "ever",
   "previous",
   "former",
   "usual",
   "previously",
   "formerly"
  ],
  "词性": [
   "adv.",
   "副词"
  ]
 },
 {
  "Chinese": "先前",
  "English": [
   "previous",
   "previously",
   "earlier",
   "prior",
   "former",
   "formerly",
   "preceding"
  ],
  "词性": [
   "adv.",
   "副词"
  ]
 }
]