[
 {
  "Chinese": "最大",
  "English": [
   "biggest",
   "largest",
   "maximum",
   "greatest",
   "most",
   "best",
   "Max"
  ],
  "词性": [
   "adj.",
   "形容词"
  ]
 },
 {
  "Chinese": "最高",
  "English": [
   "highest",
   "maximum",
   "supreme",
   "top",
   "tallest"
  ],
  "词性": [
   "adj.",
   "形容词"
  ]
 },
 {
  "Chinese": "最大限度",
  "English": [
   "maximum",
   "maximize",
   "utmost",
   "maximally",
   "furthest"
  ],
  "词性": [
   "n.",
   "名词"
  ]
 },
 {
  "Chinese": "最多",
  "English": [
   "most",
   "up",
   "maximum",
   "largest",
   "most populous",
   "Max",
   "tops"
  ],
  "词性": [
   "n.",
   "名词"
  ]
 },
 {
  "Chinese": "最大化",
  "English": [
   "maximize",
   "maximization",
   "maximum"
  ],
  "词性": [
   "adj.",
   "形容词"
  ]
 },
 {
  "Chinese": "极大",
  "English": [
   "great",
   "greatly",
   "maximum",
   "enormous",
   "tremendous",
   "maximal",
   "great deal"
  ],
  "词性": [
   "n.",
   "名词"
  ]
 },
 {
  "Chinese": "最大限度地",
  "English": [
   "maximize",
   "maximum",
   "maximally",
   "maximum limit"
  ],
  "词性": [
   "adj.",
   "形容词"
  ]
 },
 {
  "Chinese": "上限",
  "English": [
   "ceiling",
   "limit",
   "cap",
   "maximum",
   "caps",
   "upper bound",
   "capped",
   "capping"
  ],
  "词性": [
   "adj.",
   "形容词"
  ]
 }
]