[
 {
  "Chinese": "满意",
  "English": [
   "satisfaction",
   "satisfied",
   "satisfactory",
   "happy",
   "pleased",
   "satisfy",
   "dissatisfied with"
  ],
  "词性": [
   "adj.",
   "形容词"
  ]
 },
 {
  "Chinese": "令人满意",
  "English": [
   "satisfactory",
   "satisfactorily",
   "desirable",
   "gratifying"
  ],
  "词性": [
   "adj.",
   "形容词"
  ]
 },
 {
  "Chinese": "尽如人意",
  "English": [
   "satisfactory"
  ],
  "词性": [
   "adj.",
   "形容词"
  ]
 },
 {
  "Chinese": "圆满",
  "English": [
   "complete",
   "satisfactory",
   "satisfactorily",
   "successfully",
   "perfection"
  ],
  "词性": [
   "adj.",
   "形容词"
  ]
 },
 {
  "Chinese": "理想",
  "English": [
   "ideal",
   "ideals",
   "dream",
   "desired",
   "desirable",
   "satisfactory",
   "ideally"
  ],
  "词性": [
   "adj.",
   "形容词"
  ]
 }
]